<?xml version="1.0"?>
<company><item><名称>杭州数湛科技有限公司</名称><URL>http://jobs.51job.com/all/co3448296.html</URL></item><item><名称>浙江盛星文化传媒有限公司</名称><URL>http://jobs.51job.com/all/co4468906.html</URL></item><item><名称>浙江盛星文化传媒有限公司</名称><URL>http://jobs.51job.com/all/co4468906.html</URL></item><item><名称>杭州思樟科技有限公司</名称><URL>http://jobs.51job.com/all/co4310260.html</URL></item><item><名称>杭州召唤科技有限公司</名称><URL>http://jobs.51job.com/all/co3084734.html</URL></item><item><名称>杭州召唤科技有限公司</名称><URL>http://jobs.51job.com/all/co3084734.html</URL></item><item><名称>杭州宝莲灯科技有限公司</名称><URL>http://jobs.51job.com/all/co3131407.html</URL></item><item><名称>杭州宝莲灯科技有限公司</名称><URL>http://jobs.51job.com/all/co3131407.html</URL></item><item><名称>杭州宝莲灯科技有限公司</名称><URL>http://jobs.51job.com/all/co3131407.html</URL></item><item><名称>杭州宝莲灯科技有限公司</名称><URL>http://jobs.51job.com/all/co3131407.html</URL></item><item><名称>杭州宝莲灯科技有限公司</名称><URL>http://jobs.51job.com/all/co3131407.html</URL></item><item><名称>杭州宝莲灯科技有限公司</名称><URL>http://jobs.51job.com/all/co3131407.html</URL></item><item><名称>杭州宝莲灯科技有限公司</名称><URL>http://jobs.51job.com/all/co3131407.html</URL></item><item><名称>杭州宝莲灯科技有限公司</名称><URL>http://jobs.51job.com/all/co3131407.html</URL></item><item><名称>杭州宝莲灯科技有限公司</名称><URL>http://jobs.51job.com/all/co3131407.html</URL></item><item><名称>杭州宝莲灯科技有限公司</名称><URL>http://jobs.51job.com/all/co3131407.html</URL></item><item><名称>杭州宝莲灯科技有限公司</名称><URL>http://jobs.51job.com/all/co3131407.html</URL></item><item><名称>杭州宝莲灯科技有限公司</名称><URL>http://jobs.51job.com/all/co3131407.html</URL></item><item><名称>杭州晧哲教育咨询有限公司</名称><URL>http://jobs.51job.com/all/co4548053.html</URL></item><item><名称>杭州炽翼网络科技有限公司</名称><URL>http://jobs.51job.com/all/co4471464.html</URL></item><item><名称>杭州益乐网络科技有限公司</名称><URL>http://jobs.51job.com/all/co4507754.html</URL></item><item><名称>杭州益乐网络科技有限公司</名称><URL>http://jobs.51job.com/all/co4507754.html</URL></item><item><名称>杭州灿龙网络科技有限公司</名称><URL>http://jobs.51job.com/all/co4044110.html</URL></item><item><名称>杭州灿龙网络科技有限公司</名称><URL>http://jobs.51job.com/all/co4044110.html</URL></item><item><名称>杭州灿龙网络科技有限公司</名称><URL>http://jobs.51job.com/all/co4044110.html</URL></item><item><名称>杭州汇玩科技有限公司</名称><URL>http://jobs.51job.com/all/co3444076.html</URL></item><item><名称>杭州寰聚网络科技有限公司</名称><URL>http://jobs.51job.com/all/co4132367.html</URL></item><item><名称>杭州寰聚网络科技有限公司</名称><URL>http://jobs.51job.com/all/co4132367.html</URL></item><item><名称>杭州寰聚网络科技有限公司</名称><URL>http://jobs.51job.com/all/co4132367.html</URL></item><item><名称>杭州寰聚网络科技有限公司</名称><URL>http://jobs.51job.com/all/co4132367.html</URL></item><item><名称>杭州寰聚网络科技有限公司</名称><URL>http://jobs.51job.com/all/co4132367.html</URL></item><item><名称>杭州寰聚网络科技有限公司</名称><URL>http://jobs.51job.com/all/co4132367.html</URL></item><item><名称>杭州寰聚网络科技有限公司</名称><URL>http://jobs.51job.com/all/co4132367.html</URL></item><item><名称>杭州寰聚网络科技有限公司</名称><URL>http://jobs.51job.com/all/co4132367.html</URL></item><item><名称>杭州寰聚网络科技有限公司</名称><URL>http://jobs.51job.com/all/co4132367.html</URL></item><item><名称>杭州寰聚网络科技有限公司</名称><URL>http://jobs.51job.com/all/co4132367.html</URL></item><item><名称>杭州寰聚网络科技有限公司</名称><URL>http://jobs.51job.com/all/co4132367.html</URL></item><item><名称>杭州汇玩科技有限公司</名称><URL>http://jobs.51job.com/all/co3444076.html</URL></item><item><名称>杭州汇玩科技有限公司</名称><URL>http://jobs.51job.com/all/co3444076.html</URL></item><item><名称>杭州汇玩科技有限公司</名称><URL>http://jobs.51job.com/all/co3444076.html</URL></item><item><名称>杭州汇玩科技有限公司</名称><URL>http://jobs.51job.com/all/co3444076.html</URL></item><item><名称>杭州汇玩科技有限公司</名称><URL>http://jobs.51job.com/all/co3444076.html</URL></item><item><名称>杭州象文科技有限公司</名称><URL>http://jobs.51job.com/all/co3326875.html</URL></item><item><名称>浙江启冠网络股份有限公司</名称><URL>http://jobs.51job.com/all/co2816817.html</URL></item><item><名称>浙江启冠网络股份有限公司</名称><URL>http://jobs.51job.com/all/co2816817.html</URL></item><item><名称>浙江启冠网络股份有限公司</名称><URL>http://jobs.51job.com/all/co2816817.html</URL></item><item><名称>乾俸贸易（上海）股份有限公司</名称><URL>http://jobs.51job.com/all/co4524084.html</URL></item><item><名称>乾俸贸易（上海）股份有限公司</名称><URL>http://jobs.51job.com/all/co4524084.html</URL></item><item><名称>乾俸贸易（上海）股份有限公司</名称><URL>http://jobs.51job.com/all/co4524084.html</URL></item></company>
