<?xml version="1.0"?>
<company><item><名称>杭州漫禾科技有限公司</名称><URL>http://jobs.51job.com/all/co4413036.html</URL></item><item><名称>杭州彩菱科技有限公司</名称><URL>http://jobs.51job.com/all/co3274390.html</URL></item><item><名称>杭州多多猫软件有限公司</名称><URL>http://jobs.51job.com/all/co3243130.html</URL></item><item><名称>杭州黑岩网络科技有限公司</名称><URL>http://jobs.51job.com/all/co3579913.html</URL></item><item><名称>浙江盛和网络科技有限公司</名称><URL>http://jobs.51job.com/all/co2964869.html</URL></item><item><名称>浙江盛和网络科技有限公司</名称><URL>http://jobs.51job.com/all/co2964869.html</URL></item><item><名称>浙江盛和网络科技有限公司</名称><URL>http://jobs.51job.com/all/co2964869.html</URL></item><item><名称>浙江盛和网络科技有限公司</名称><URL>http://jobs.51job.com/all/co2964869.html</URL></item><item><名称>浙江盛和网络科技有限公司</名称><URL>http://jobs.51job.com/all/co2964869.html</URL></item><item><名称>浙江盛和网络科技有限公司</名称><URL>http://jobs.51job.com/all/co2964869.html</URL></item><item><名称>浙江盛和网络科技有限公司</名称><URL>http://jobs.51job.com/all/co2964869.html</URL></item><item><名称>浙江盛和网络科技有限公司</名称><URL>http://jobs.51job.com/all/co2964869.html</URL></item><item><名称>浙江盛和网络科技有限公司</名称><URL>http://jobs.51job.com/all/co2964869.html</URL></item><item><名称>浙江盛和网络科技有限公司</名称><URL>http://jobs.51job.com/all/co2964869.html</URL></item><item><名称>浙江盛和网络科技有限公司</名称><URL>http://jobs.51job.com/all/co2964869.html</URL></item><item><名称>浙江盛和网络科技有限公司</名称><URL>http://jobs.51job.com/all/co2964869.html</URL></item><item><名称>浙江盛和网络科技有限公司</名称><URL>http://jobs.51job.com/all/co2964869.html</URL></item><item><名称>浙江盛和网络科技有限公司</名称><URL>http://jobs.51job.com/all/co2964869.html</URL></item><item><名称>浙江盛和网络科技有限公司</名称><URL>http://jobs.51job.com/all/co2964869.html</URL></item><item><名称>浙江盛和网络科技有限公司</名称><URL>http://jobs.51job.com/all/co2964869.html</URL></item><item><名称>浙江盛和网络科技有限公司</名称><URL>http://jobs.51job.com/all/co2964869.html</URL></item><item><名称>浙江盛和网络科技有限公司</名称><URL>http://jobs.51job.com/all/co2964869.html</URL></item><item><名称>浙江盛和网络科技有限公司</名称><URL>http://jobs.51job.com/all/co2964869.html</URL></item><item><名称>浙江盛和网络科技有限公司</名称><URL>http://jobs.51job.com/all/co2964869.html</URL></item><item><名称>浙江盛和网络科技有限公司</名称><URL>http://jobs.51job.com/all/co2964869.html</URL></item><item><名称>浙江盛和网络科技有限公司</名称><URL>http://jobs.51job.com/all/co2964869.html</URL></item><item><名称>浙江盛和网络科技有限公司</名称><URL>http://jobs.51job.com/all/co2964869.html</URL></item><item><名称>杭州第九区科技有限公司</名称><URL>http://jobs.51job.com/all/co3859105.html</URL></item><item><名称>杭州东九网络科技有限公司</名称><URL>http://jobs.51job.com/all/co3668582.html</URL></item><item><名称>杭州东九网络科技有限公司</名称><URL>http://jobs.51job.com/all/co3668582.html</URL></item><item><名称>杭州东九网络科技有限公司</名称><URL>http://jobs.51job.com/all/co3668582.html</URL></item><item><名称>杭州东九网络科技有限公司</名称><URL>http://jobs.51job.com/all/co3668582.html</URL></item><item><名称>杭州东九网络科技有限公司</名称><URL>http://jobs.51job.com/all/co3668582.html</URL></item><item><名称>杭州东九网络科技有限公司</名称><URL>http://jobs.51job.com/all/co3668582.html</URL></item><item><名称>杭州东九网络科技有限公司</名称><URL>http://jobs.51job.com/all/co3668582.html</URL></item><item><名称>杭州东九网络科技有限公司</名称><URL>http://jobs.51job.com/all/co3668582.html</URL></item><item><名称>杭州东九网络科技有限公司</名称><URL>http://jobs.51job.com/all/co3668582.html</URL></item><item><名称>杭州馒头科技有限公司</名称><URL>http://jobs.51job.com/all/co3434320.html</URL></item><item><名称>杭州馒头科技有限公司</名称><URL>http://jobs.51job.com/all/co3434320.html</URL></item><item><名称>杭州馒头科技有限公司</名称><URL>http://jobs.51job.com/all/co3434320.html</URL></item><item><名称>杭州馒头科技有限公司</名称><URL>http://jobs.51job.com/all/co3434320.html</URL></item><item><名称>网易集团</名称><URL>http://jobs.51job.com/all/co3645991.html</URL></item><item><名称>网易集团</名称><URL>http://jobs.51job.com/all/co3645991.html</URL></item><item><名称>网易集团</名称><URL>http://jobs.51job.com/all/co3645991.html</URL></item><item><名称>网易集团</名称><URL>http://jobs.51job.com/all/co3645991.html</URL></item><item><名称>网易集团</名称><URL>http://jobs.51job.com/all/co3645991.html</URL></item><item><名称>网易集团</名称><URL>http://jobs.51job.com/all/co3645991.html</URL></item><item><名称>网易集团</名称><URL>http://jobs.51job.com/all/co3645991.html</URL></item><item><名称>杭州叉乘文化创意有限公司</名称><URL>http://jobs.51job.com/all/co4362676.html</URL></item></company>
